gitlabci_lint/__init__.py
gitlabci_lint/gitlab-ci.json
gitlabci_jsonschema_lint-0.0.3.dist-info/LICENSE
gitlabci_jsonschema_lint-0.0.3.dist-info/METADATA
gitlabci_jsonschema_lint-0.0.3.dist-info/WHEEL
gitlabci_jsonschema_lint-0.0.3.dist-info/entry_points.txt
gitlabci_jsonschema_lint-0.0.3.dist-info/top_level.txt
gitlabci_jsonschema_lint-0.0.3.dist-info/RECORD
