Metadata-Version: 2.1
Name: gitlabci-jsonschema-lint
Version: 0.0.3
Summary: Python library to lint .gitlab-ci.yml files
Home-page: https://github.com/bagerard/gitlabci-jsonschema-lint
Maintainer: Bastien Gerard
Maintainer-email: bast.gerard@gmail.com
License: MIT License
Keywords: gitlab-ci linter
Platform: UNKNOWN
Classifier: Programming Language :: Python :: 3
Classifier: Topic :: Software Development :: Quality Assurance
Requires-Dist: jsonschema (>=3.0.0)
Requires-Dist: ruamel.yaml (>=0.16.0)
